README.md
setup.py
webtypes/__init__.py
webtypes/compat.py
webtypes/conneg.py
webtypes/document.py
webtypes/exceptions.py
webtypes/formats.py
webtypes/http.py
webtypes/main.py
webtypes/parse.py
webtypes/test.py
webtypes/types.py
webtypes/utils.py
webtypes/validators.py
webtypes.egg-info/PKG-INFO
webtypes.egg-info/SOURCES.txt
webtypes.egg-info/dependency_links.txt
webtypes.egg-info/entry_points.txt
webtypes.egg-info/requires.txt
webtypes.egg-info/top_level.txt
webtypes/client/__init__.py
webtypes/client/auth.py
webtypes/client/client.py
webtypes/client/transports.py
webtypes/client/utils.py
webtypes/codecs/__init__.py
webtypes/codecs/base.py
webtypes/codecs/config.py
webtypes/codecs/download.py
webtypes/codecs/jsondata.py
webtypes/codecs/jsonschema.py
webtypes/codecs/multipart.py
webtypes/codecs/openapi.py
webtypes/codecs/swagger.py
webtypes/codecs/text.py
webtypes/codecs/urlencoded.py
webtypes/server/__init__.py
webtypes/server/adapters.py
webtypes/server/app.py
webtypes/server/asgi.py
webtypes/server/components.py
webtypes/server/core.py
webtypes/server/handlers.py
webtypes/server/injector.py
webtypes/server/router.py
webtypes/server/staticfiles.py
webtypes/server/templates.py
webtypes/server/validation.py
webtypes/server/wsgi.py
webtypes/static/css/base.css
webtypes/static/css/bootstrap.min.css
webtypes/static/css/font-awesome-4.0.3.css
webtypes/static/css/highlight.css
webtypes/static/css/jquery.json-view.min.css
webtypes/static/fonts/fontawesome-webfont.eot
webtypes/static/fonts/fontawesome-webfont.svg
webtypes/static/fonts/fontawesome-webfont.ttf
webtypes/static/fonts/fontawesome-webfont.woff
webtypes/static/fonts/glyphicons-halflings-regular.eot
webtypes/static/fonts/glyphicons-halflings-regular.svg
webtypes/static/fonts/glyphicons-halflings-regular.ttf
webtypes/static/fonts/glyphicons-halflings-regular.woff
webtypes/static/fonts/glyphicons-halflings-regular.woff2
webtypes/static/img/favicon.ico
webtypes/static/img/grid.png
webtypes/static/img/gripper.png
webtypes/static/img/logomarque-small-white.png
webtypes/static/js/bootstrap.min.js
webtypes/static/js/coreapi-0.1.0.js
webtypes/static/js/highlight.pack.js
webtypes/static/js/jquery-1.10.2.min.js
